shikoni/ShikoniClasses.py
shikoni/__init__.py
shikoni/shikoni_main.py
shikoni/base_messages/MessageType.py
shikoni/base_messages/ShikoniMessageAddConnector.py
shikoni/base_messages/ShikoniMessageAddConnectorGroup.py
shikoni/base_messages/ShikoniMessageAddConnectorToGroup.py
shikoni/base_messages/ShikoniMessageConnectorName.py
shikoni/base_messages/ShikoniMessageConnectorSocket.py
shikoni/base_messages/ShikoniMessageRemoveConnector.py
shikoni/base_messages/ShikoniMessageRemoveConnectorFromGroup.py
shikoni/base_messages/ShikoniMessageRemoveConnectorGroup.py
shikoni/base_messages/__init__.py
shikoni/data/MessageTypeClasses.py
shikoni/data/__init__.py
shikoni/data/massage_type_classes.json
shikoni/ideas/__init__.py
shikoni/ideas/message.txt
shikoni/interfaces/ShikoniMessage.py
shikoni/interfaces/__init__.py
shikoni/message_types/ShikoniMessageClear.py
shikoni/message_types/ShikoniMessageRun.py
shikoni/message_types/ShikoniMessageString.py
shikoni/message_types/__init__.py
shikoni/tools/ClientConnector.py
shikoni/tools/PackageController.py
shikoni/tools/ServerConnector.py
shikoni/tools/ShikoniInfo.py
shikoni/tools/__init__.py
shikoni/tools/host_info.py
shikoni-0.0.2.dist-info/METADATA
shikoni-0.0.2.dist-info/WHEEL
shikoni-0.0.2.dist-info/licenses/LICENSE
shikoni-0.0.2.dist-info/RECORD
