Metadata-Version: 2.1
Name: shikoni
Version: 0.0.2
Summary: Message system for connecting tools on a single or multiple Computer.
Project-URL: Github, https://github.com/VGDragon/shikoni
Author-email: VG Dragon <vg_dragon@hotmail.com>
License-File: LICENSE
Classifier: License :: OSI Approved :: MIT License
Classifier: Operating System :: OS Independent
Classifier: Programming Language :: Python :: 3
Requires-Python: >=3.8
